setup.py
RSA_Cipher/RSA.py
RSA_Cipher/__init__.py
RSA_Cipher/congruence.py
RSA_Cipher/decryptRSA.py
RSA_Cipher/encryptRSA.py
RSA_Cipher/gcd.py
RSA_Cipher/modExp.py
RSA_Cipher/prime.py
RSA_Cipher.egg-info/PKG-INFO
RSA_Cipher.egg-info/SOURCES.txt
RSA_Cipher.egg-info/dependency_links.txt
RSA_Cipher.egg-info/entry_points.txt
RSA_Cipher.egg-info/requires.txt
RSA_Cipher.egg-info/top_level.txt